landslideml/__init__.py
landslideml/config.py
landslideml/model.py
landslideml/output.py
landslideml/reader.py
landslideml-1.0.1.dist-info/LICENSE
landslideml-1.0.1.dist-info/METADATA
landslideml-1.0.1.dist-info/WHEEL
landslideml-1.0.1.dist-info/top_level.txt
landslideml-1.0.1.dist-info/RECORD
