Metadata-Version: 2.1
Name: landslideml
Version: 1.0.1
Summary: A package for generation of landslide susceptibility mapping with ML models
Home-page: https://github.com/ImProta/LandslideML
Author: Victor Improta
Author-email: Victor Improta <victor.improta.moreira@rwth-aachen.de>
Project-URL: homepage, https://github.com/ImProta/LandslideML
Project-URL: issues, https://github.com/ImProta/LandslideML/issues
Classifier: Intended Audience :: Developers
Classifier: Intended Audience :: Science/Research
Classifier: License :: OSI Approved :: MIT License
Classifier: Programming Language :: Python :: 3.12
Classifier: Operating System :: OS Independent
Classifier: Topic :: Scientific/Engineering
Requires-Python: >=3.12
License-File: LICENSE
Requires-Dist: numpy
Requires-Dist: pandas
Requires-Dist: scikit-learn
Requires-Dist: matplotlib
Requires-Dist: geopandas
Requires-Dist: seaborn
Requires-Dist: joblib
Requires-Dist: netcdf4
Requires-Dist: xarray
Provides-Extra: dev
Requires-Dist: pytest ; extra == 'dev'
Requires-Dist: black ; extra == 'dev'
